capi_param_builder/__init__.py
capi_param_builder/param_builder.py
capi_param_builder/release_config.py
capi_param_builder/model/__init__.py
capi_param_builder/model/cookie_settings.py
capi_param_builder/model/fbc_param_configs.py
capi_param_builder/util/__init__.py
capi_param_builder/util/etld_plus_one_resolver.py
test/__init__.py
test/test_etld_plus_one_resolver.py
test/test_param_builder.py
capi_param_builder_python-1.1.2.dist-info/METADATA
capi_param_builder_python-1.1.2.dist-info/WHEEL
capi_param_builder_python-1.1.2.dist-info/top_level.txt
capi_param_builder_python-1.1.2.dist-info/RECORD
