Metadata-Version: 2.4
Name: capi_param_builder_python
Version: 1.1.2
Summary: Parameter builder SDK for Conversion API events
Dynamic: summary
